PyReactLab/__init__.py
PyReactLab/app.py
PyReactLab/configs/__init__.py
PyReactLab/configs/constants.py
PyReactLab/configs/setting.py
PyReactLab/docs/__init__.py
PyReactLab/docs/chemicalpotential.py
PyReactLab/docs/gasreactions.py
PyReactLab/docs/liquidreactions.py
PyReactLab/docs/optim.py
PyReactLab/docs/reaction.py
PyReactLab/docs/reactionanalyzer.py
PyReactLab/docs/reactionsystem.py
PyReactLab/docs/refmanager.py
PyReactLab/docs/source.py
PyReactLab/docs/thermolinkdb.py
PyReactLab/docs/thermomodels.py
PyReactLab/models/__init__.py
PyReactLab/models/properties.py
PyReactLab/phase/__init__.py
PyReactLab/phase/main.py
PyReactLab/phase/phasecontroller.py
PyReactLab/plugin/reference.yml
PyReactLab/thermo/__init__.py
PyReactLab/thermo/models.py
PyReactLab/thermo/source.py
PyReactLab/utils/__init__.py
PyReactLab/utils/chemreact.py
PyReactLab/utils/postproc.py
PyReactLab/utils/refs.py
PyReactLab/utils/tools.py
pyreactlab-0.3.1.dist-info/licenses/LICENSE
pyreactlab-0.3.1.dist-info/METADATA
pyreactlab-0.3.1.dist-info/WHEEL
pyreactlab-0.3.1.dist-info/top_level.txt
pyreactlab-0.3.1.dist-info/RECORD
