Metadata-Version: 2.4
Name: PyReactLab
Version: 0.3.1
Summary: PyReactLab is an open-source Python package designed to analyze chemical reactions and theoretically assess their thermodynamic feasibility.
Author: Sina Gilassi
Author-email: Sina Gilassi <sina.gilassi@gmail.com>
License-Expression: MIT
Project-URL: Homepage, https://github.com/sinagilassi/PyReactLab
Project-URL: Bug Tracker, https://github.com/sinagilassi/PyReactLab/issues
Project-URL: Repository, https://github.com/sinagilassi/PyReactLab
Project-URL: Documentation, https://pyreactlab.readthedocs.io/en/latest/
Keywords: python,chemical-engineering,process-modeling,reaction-analysis,equilibrium-constant,kinetics,thermodynamic-analysis,reaction-kinetics,thermodynamics
Classifier: Development Status :: 3 - Alpha
Classifier: Intended Audience :: Education
Classifier: Intended Audience :: Science/Research
Classifier: Topic :: Scientific/Engineering :: Chemistry
Classifier: Programming Language :: Python :: 3.10
Classifier: Operating System :: Unix
Classifier: Operating System :: MacOS :: MacOS X
Classifier: Operating System :: Microsoft :: Windows
Requires-Python: >=3.10
License-File: LICENSE
Requires-Dist: pydantic>=2.11.7
Requires-Dist: pydantic-settings>=2.10.1
Requires-Dist: pyyaml>=6.0.2
Requires-Dist: pythermodb
Requires-Dist: pythermodb-settings
Requires-Dist: pythermomodels
Requires-Dist: pycuc
Provides-Extra: plotting
Requires-Dist: matplotlib; extra == "plotting"
Dynamic: author
Dynamic: license-file
Dynamic: requires-python
